<?xml version="1.0" encoding="UTF-8" ?>
<resource_file type="PackedScene" subresource_count="5" version="1.0" version_name="Godot Engine v1.0.3917-beta1">
	<ext_resource path="res://tank_color_animation.xml" type="PackedScene"></ext_resource>
	<ext_resource path="res://hud.gd" type="Script"></ext_resource>
	<ext_resource path="res://assets/bionickid.fnt" type="Font"></ext_resource>
	<resource type="Animation" path="local://1">
		<string name="resource/name"> "victory" </string>
		<real name="length"> 1 </real>
		<bool name="loop"> False </bool>
		<real name="step"> 0.1 </real>
		<string name="tracks/0/type"> "value" </string>
		<node_path name="tracks/0/path"> ".:rect/pos" </node_path>
		<int name="tracks/0/interp"> 2 </int>
		<dictionary name="tracks/0/keys" shared="false">
			<string> "cont" </string>
			<bool> True </bool>
			<string> "transitions" </string>
			<real_array  len="2"> 				1, 19.0273 </real_array>
			<string> "values" </string>
			<array  len="2" shared="false">
				<vector2> 505, -85 </vector2>
				<vector2> 534, 533 </vector2>
			</array>
			<string> "times" </string>
			<real_array  len="2"> 				0, 1 </real_array>
		</dictionary>

	</resource>
	<main_resource>
		<dictionary name="_bundled" shared="false">
			<string> "names" </string>
			<string_array  len="58">
				<string> "scoreboard" </string>
				<string> "CanvasLayer" </string>
				<string> "layer" </string>
				<string> "offset" </string>
				<string> "rotation" </string>
				<string> "scale" </string>
				<string> "script/script" </string>
				<string> "__meta__" </string>
				<string> "tank1" </string>
				<string> "Control" </string>
				<string> "visibility/visible" </string>
				<string> "visibility/opacity" </string>
				<string> "visibility/self_opacity" </string>
				<string> "visibility/behind_parent" </string>
				<string> "margin/right" </string>
				<string> "margin/bottom" </string>
				<string> "focus_neighbour/left" </string>
				<string> "focus_neighbour/top" </string>
				<string> "focus_neighbour/right" </string>
				<string> "focus_neighbour/bottom" </string>
				<string> "focus/ignore_mouse" </string>
				<string> "focus/stop_mouse" </string>
				<string> "size_flags/horizontal" </string>
				<string> "size_flags/vertical" </string>
				<string> "size_flags/stretch_ratio" </string>
				<string> "Node2D" </string>
				<string> "transform/pos" </string>
				<string> "x" </string>
				<string> "Label" </string>
				<string> "margin/left" </string>
				<string> "margin/top" </string>
				<string> "custom_fonts/font" </string>
				<string> "range/min" </string>
				<string> "range/max" </string>
				<string> "range/step" </string>
				<string> "range/page" </string>
				<string> "range/value" </string>
				<string> "range/exp_edit" </string>
				<string> "rounded_values" </string>
				<string> "text" </string>
				<string> "align" </string>
				<string> "valign" </string>
				<string> "autowrap" </string>
				<string> "uppercase" </string>
				<string> "percent_visible" </string>
				<string> "lives" </string>
				<string> "tank2" </string>
				<string> "victory" </string>
				<string> "anim" </string>
				<string> "AnimationPlayer" </string>
				<string> "playback/process_mode" </string>
				<string> "playback/default_blend_time" </string>
				<string> "root/root" </string>
				<string> "anims/victory" </string>
				<string> "playback/active" </string>
				<string> "playback/speed" </string>
				<string> "blend_times" </string>
				<string> "autoplay" </string>
			</string_array>
			<string> "version" </string>
			<int> 1 </int>
			<string> "conn_count" </string>
			<int> 0 </int>
			<string> "node_count" </string>
			<int> 11 </int>
			<string> "variants" </string>
			<array  len="40" shared="false">
				<int> 1 </int>
				<vector2> 0, 0 </vector2>
				<real> 0 </real>
				<vector2> 1, 1 </vector2>
				<resource  resource_type="Script" path="res://hud.gd">  </resource>
				<dictionary  shared="false">
					<string> "__editor_plugin_states__" </string>
					<dictionary  shared="false">
						<string> "Script" </string>
						<dictionary  shared="false">
							<string> "current" </string>
							<int> 4 </int>
							<string> "sources" </string>
							<array  len="5" shared="false">
								<string> "res://tank.gd" </string>
								<string> "res://main.gd" </string>
								<string> "res://title.gd" </string>
								<string> "res://global.gd" </string>
								<string> "res://hud.gd" </string>
							</array>
						</dictionary>
						<string> "2D" </string>
						<dictionary  shared="false">
							<string> "pixel_snap" </string>
							<bool> False </bool>
							<string> "zoom" </string>
							<real> 0.598737 </real>
							<string> "use_snap" </string>
							<bool> False </bool>
							<string> "ofs" </string>
							<vector2> -138.355, -130.767 </vector2>
							<string> "snap" </string>
							<int> 10 </int>
						</dictionary>
						<string> "3D" </string>
						<dictionary  shared="false">
							<string> "zfar" </string>
							<real> 500 </real>
							<string> "fov" </string>
							<real> 45 </real>
							<string> "viewports" </string>
							<array  len="4" shared="false">
								<dictionary  shared="false">
									<string> "distance" </string>
									<real> 4 </real>
									<string> "x_rot" </string>
									<real> 0 </real>
									<string> "y_rot" </string>
									<real> 0 </real>
									<string> "use_orthogonal" </string>
									<bool> False </bool>
									<string> "use_environment" </string>
									<bool> False </bool>
									<string> "pos" </string>
									<vector3> 0, 0, 0 </vector3>
								</dictionary>
								<dictionary  shared="false">
									<string> "distance" </string>
									<real> 4 </real>
									<string> "x_rot" </string>
									<real> 0 </real>
									<string> "y_rot" </string>
									<real> 0 </real>
									<string> "use_orthogonal" </string>
									<bool> False </bool>
									<string> "use_environment" </string>
									<bool> False </bool>
									<string> "pos" </string>
									<vector3> 0, 0, 0 </vector3>
								</dictionary>
								<dictionary  shared="false">
									<string> "distance" </string>
									<real> 4 </real>
									<string> "x_rot" </string>
									<real> 0 </real>
									<string> "y_rot" </string>
									<real> 0 </real>
									<string> "use_orthogonal" </string>
									<bool> False </bool>
									<string> "use_environment" </string>
									<bool> False </bool>
									<string> "pos" </string>
									<vector3> 0, 0, 0 </vector3>
								</dictionary>
								<dictionary  shared="false">
									<string> "distance" </string>
									<real> 4 </real>
									<string> "x_rot" </string>
									<real> 0 </real>
									<string> "y_rot" </string>
									<real> 0 </real>
									<string> "use_orthogonal" </string>
									<bool> False </bool>
									<string> "use_environment" </string>
									<bool> False </bool>
									<string> "pos" </string>
									<vector3> 0, 0, 0 </vector3>
								</dictionary>
							</array>
							<string> "viewport_mode" </string>
							<int> 1 </int>
							<string> "default_light" </string>
							<bool> True </bool>
							<string> "show_grid" </string>
							<bool> True </bool>
							<string> "show_origin" </string>
							<bool> True </bool>
							<string> "znear" </string>
							<real> 0.1 </real>
						</dictionary>
					</dictionary>
					<string> "__editor_run_settings__" </string>
					<dictionary  shared="false">
						<string> "custom_args" </string>
						<string> "-l $scene" </string>
						<string> "run_mode" </string>
						<int> 0 </int>
					</dictionary>
					<string> "__editor_plugin_screen__" </string>
					<string> "2D" </string>
				</dictionary>
				<bool> True </bool>
				<real> 1 </real>
				<bool> False </bool>
				<real> 40 </real>
				<node_path> "" </node_path>
				<int> 2 </int>
				<resource  resource_type="PackedScene" path="res://tank_color_animation.xml">  </resource>
				<vector2> 125.154, 99.3073 </vector2>
				<real> 205 </real>
				<real> 91 </real>
				<real> 246 </real>
				<real> 109 </real>
				<resource  resource_type="Font" path="res://assets/bionickid.fnt">  </resource>
				<string> "x" </string>
				<int> 0 </int>
				<real> -1 </real>
				<real> 265 </real>
				<real> 90 </real>
				<real> 348 </real>
				<real> 161 </real>
				<string> "3" </string>
				<real> 285 </real>
				<real> -2 </real>
				<real> 325 </real>
				<real> 38 </real>
				<real> 505 </real>
				<real> -85 </real>
				<real> 719 </real>
				<real> -67 </real>
				<string> "Tank WINS" </string>
				<node_path> ".." </node_path>
				<resource  resource_type="Animation" path="local://1">  </resource>
				<array  len="0" shared="false">
				</array>
				<string> "victory" </string>
			</array>
			<string> "nodes" </string>
			<int_array  len="473"> 				-1, -1, 1, 0, -1, 6, 2, 0, 3, 1, 4, 2, 5, 3, 6, 4, 7, 5, 0, 0, 0, 9, 8, -1, 15, 10, 6, 11, 7, 12, 7, 13, 8, 14, 9, 15, 9, 16, 10, 17, 10, 18, 10, 19, 10, 20, 8, 21, 6, 22, 11, 23, 11, 24, 7, 0, 1, 0, 25, 9, 12, 1, 26, 13, 0, 1, 0, 28, 27, -1, 30, 10, 6, 11, 7, 12, 7, 13, 8, 29, 14, 30, 15, 14, 16, 15, 17, 16, 10, 17, 10, 18, 10, 19, 10, 20, 6, 21, 6, 22, 11, 24, 7, 31, 18, 32, 2, 33, 7, 34, 7, 35, 7, 36, 2, 37, 8, 38, 8, 39, 19, 40, 20, 41, 20, 42, 8, 43, 8, 44, 21, 0, 1, 0, 28, 45, -1, 30, 10, 6, 11, 7, 12, 7, 13, 8, 29, 22, 30, 23, 14, 24, 15, 25, 16, 10, 17, 10, 18, 10, 19, 10, 20, 6, 21, 6, 22, 0, 24, 7, 31, 18, 32, 2, 33, 7, 34, 7, 35, 7, 36, 2, 37, 8, 38, 8, 39, 26, 40, 20, 41, 20, 42, 8, 43, 8, 44, 21, 0, 0, 0, 9, 46, -1, 17, 10, 6, 11, 7, 12, 7, 13, 8, 29, 27, 30, 28, 14, 29, 15, 30, 16, 10, 17, 10, 18, 10, 19, 10, 20, 8, 21, 6, 22, 11, 23, 11, 24, 7, 0, 5, 0, 25, 9, 12, 1, 26, 13, 0, 5, 0, 28, 27, -1, 30, 10, 6, 11, 7, 12, 7, 13, 8, 29, 14, 30, 15, 14, 16, 15, 17, 16, 10, 17, 10, 18, 10, 19, 10, 20, 6, 21, 6, 22, 11, 24, 7, 31, 18, 32, 2, 33, 7, 34, 7, 35, 7, 36, 2, 37, 8, 38, 8, 39, 19, 40, 20, 41, 20, 42, 8, 43, 8, 44, 21, 0, 5, 0, 28, 45, -1, 30, 10, 6, 11, 7, 12, 7, 13, 8, 29, 22, 30, 23, 14, 24, 15, 25, 16, 10, 17, 10, 18, 10, 19, 10, 20, 6, 21, 6, 22, 0, 24, 7, 31, 18, 32, 2, 33, 7, 34, 7, 35, 7, 36, 2, 37, 8, 38, 8, 39, 26, 40, 20, 41, 20, 42, 8, 43, 8, 44, 21, 0, 0, 0, 28, 47, -1, 30, 10, 6, 11, 7, 12, 7, 13, 8, 29, 31, 30, 32, 14, 33, 15, 34, 16, 10, 17, 10, 18, 10, 19, 10, 20, 6, 21, 6, 22, 11, 24, 7, 31, 18, 32, 2, 33, 7, 34, 7, 35, 7, 36, 2, 37, 8, 38, 8, 39, 35, 40, 20, 41, 20, 42, 8, 43, 8, 44, 21, 0, 9, 0, 49, 48, -1, 8, 50, 0, 51, 2, 52, 36, 53, 37, 54, 6, 55, 7, 56, 38, 57, 39, 0 </int_array>
			<string> "conns" </string>
			<int_array  len="0"> 				 </int_array>
		</dictionary>

	</main_resource>
</resource_file>